layer_sdk/__init__.py
layer_sdk/_default_client.py
layer_sdk/_platform.py
layer_sdk/_utils.py
layer_sdk/_version.py
layer_sdk/auth.py
layer_sdk/client.py
layer_sdk/exceptions.py
layer_sdk/instrumentation/__init__.py
layer_sdk/instrumentation/_anthropic.py
layer_sdk/instrumentation/_base.py
layer_sdk/instrumentation/_openai.py
layer_sdk/logger.py
layer_sdk/py.typed
layer_sdk/schemas.py
protectai_layer_sdk-0.14.0.dist-info/METADATA
protectai_layer_sdk-0.14.0.dist-info/WHEEL
protectai_layer_sdk-0.14.0.dist-info/RECORD
